[{"idproducto":"20201125071013","id":"20201125072831","nombre":"Sebasti\u00e1n","mensaje":"Muy rica la pizza"},{"idproducto":"20201125074246","id":"20201125075641","nombre":"Sebasti\u00e1n","mensaje":"Muy rica la pizza"},{"idproducto":"20201125074246","id":"20201125085002","nombre":"ezequielon","mensaje":"altas pizzas"},{"idproducto":"20201125080146","id":"20201125085854","nombre":"Sebasti\u00e1n","mensaje":"Me gusta pepita la pistolera"},{"idproducto":"20201125074246","id":"20201125095341","nombre":"Carlos","mensaje":"Me gusto mucho esta pizza realmente"},{"idproducto":"20201125094644","id":"20201125095419","nombre":"Damian","mensaje":"Mas rica que la pizza de muzzarella"},{"idproducto":"20201125074246","id":"20201125112634","nombre":"Pedro","mensaje":"Me ha gustado bastante"},{"idproducto":"20201125094644","id":"20201125112714","nombre":"Ezequiel","mensaje":"La calidad del morron es excelente"},{"idproducto":"20201125113002","id":"20201125113125","nombre":"Rodrigo","mensaje":"La mejor hamburguesa que he probado"},{"idproducto":"20201125074246","id":"20201126015355","nombre":"Flavio","mensaje":"Muy buena pizza"},{"idproducto":"20201125094854","id":"20201126015455","nombre":"Sebastian","mensaje":"muy buena hamburguesa"},{"idproducto":"20201126015725","id":"20201126015749","nombre":"pablo","mensaje":"excelente bebida"}]